Metadata-Version: 1.0
Name: svmpy
Version: 0.2
Summary: Naive SVM library in Python
Home-page: http://github.com/ajtulloch/svmpy
Author: Andrew Tulloch
Author-email: andrew@tullo.ch
License: MIT
Platform: UNKNOWN
